odoo10_addon_purchase_sale_inter_company-10.0.1.0.0.99.dev12-py2.7-nspkg.pth
odoo/addons/purchase_sale_inter_company/README.rst
odoo/addons/purchase_sale_inter_company/__init__.py
odoo/addons/purchase_sale_inter_company/__manifest__.py
odoo/addons/purchase_sale_inter_company/demo/inter_company_purchase_sale.xml
odoo/addons/purchase_sale_inter_company/i18n/fr.po
odoo/addons/purchase_sale_inter_company/i18n/purchase_sale_inter_company.pot
odoo/addons/purchase_sale_inter_company/models/__init__.py
odoo/addons/purchase_sale_inter_company/models/account_invoice.py
odoo/addons/purchase_sale_inter_company/models/purchase.py
odoo/addons/purchase_sale_inter_company/models/res_company.py
odoo/addons/purchase_sale_inter_company/models/sale.py
odoo/addons/purchase_sale_inter_company/models/sale_config_settings.py
odoo/addons/purchase_sale_inter_company/static/description/icon.png
odoo/addons/purchase_sale_inter_company/tests/__init__.py
odoo/addons/purchase_sale_inter_company/tests/test_inter_company_purchase_sale.py
odoo/addons/purchase_sale_inter_company/views/purchase_views.xml
odoo/addons/purchase_sale_inter_company/views/res_company_view.xml
odoo/addons/purchase_sale_inter_company/views/sale_config_settings_views.xml
odoo10_addon_purchase_sale_inter_company-10.0.1.0.0.99.dev12.dist-info/METADATA
odoo10_addon_purchase_sale_inter_company-10.0.1.0.0.99.dev12.dist-info/RECORD
odoo10_addon_purchase_sale_inter_company-10.0.1.0.0.99.dev12.dist-info/WHEEL
odoo10_addon_purchase_sale_inter_company-10.0.1.0.0.99.dev12.dist-info/namespace_packages.txt
odoo10_addon_purchase_sale_inter_company-10.0.1.0.0.99.dev12.dist-info/top_level.txt
